tfdata/__init__.py
tfdata/test_stra.py
tfdata/tfclient.py
tfdata/menu_text/att_list.py
tfdata/menu_text/menu_text0.py
tfdata/menu_text/update_note.py
tfdata/utils/TF_utils.py
tfdata/utils/__init__.py
tfdata/utils/comm_utils.py
tfdata/utils/network_utils.py
tfdata-0.5.4.dist-info/METADATA
tfdata-0.5.4.dist-info/WHEEL
tfdata-0.5.4.dist-info/top_level.txt
tfdata-0.5.4.dist-info/RECORD
