Metadata-Version: 2.1
Name: tfdata
Version: 0.5.4
Summary: NA
Home-page: https://github.com/edwincca/tfdata/blob/master/README.md
Author: DrEdw
Author-email: ed@topfintech.org
License: UNKNOWN
Platform: UNKNOWN
Classifier: Programming Language :: Python :: 3
Classifier: License :: OSI Approved :: MIT License
Classifier: Operating System :: OS Independent
Requires-Dist: tdautils
Requires-Dist: numpy
Requires-Dist: pandas
